LICENSE.txt
README.md
setup.cfg
setup.py
sm4_utils/__init__.py
sm4_utils/sm4.py
sm4_utils.egg-info/PKG-INFO
sm4_utils.egg-info/SOURCES.txt
sm4_utils.egg-info/dependency_links.txt
sm4_utils.egg-info/requires.txt
sm4_utils.egg-info/top_level.txt